{
  "12347": {
    "HWH": [
      {
        "stnCode": "LLH",
        "stnName": "LILUAH",
        "arrival": "12:04",
        "departure": "12:04"
      },
      {
        "stnCode": "BEQ",
        "stnName": "BELUR",
        "arrival": "12:05",
        "departure": "12:05"
      },
      {
        "stnCode": "BLY",
        "stnName": "BALLY",
        "arrival": "12:07",
        "departure": "12:07"
      },
      {
        "stnCode": "BZL",
        "stnName": "BELANAGAR",
        "arrival": "12:09",
        "departure": "12:09"
      },
      {
        "stnCode": "DKAE",
        "stnName": "DANKUNI",
        "arrival": "12:12",
        "departure": "12:12"
      },
      {
        "stnCode": "GBRA",
        "stnName": "GOBRA",
        "arrival": "12:14",
        "departure": "12:14"
      },
      {
        "stnCode": "JOX",
        "stnName": "JANAI ROAD",
        "arrival": "12:17",
        "departure": "12:17"
      },
      {
        "stnCode": "BPAE",
        "stnName": "BEGUMPUR",
        "arrival": "12:19",
        "departure": "12:19"
      },
      {
        "stnCode": "BRPA",
        "stnName": "BARUIPARA",
        "arrival": "12:22",
        "departure": "12:22"
      },
      {
        "stnCode": "MBE",
        "stnName": "MIRZAPUR BANKIPUR",
        "arrival": "12:25",
        "departure": "12:25"
      },
      {
        "stnCode": "BLAE",
        "stnName": "BALARAMBATI",
        "arrival": "12:27",
        "departure": "12:27"
      },
      {
        "stnCode": "KQU",
        "stnName": "KAMARKUNDU",
        "arrival": "12:28",
        "departure": "12:29"
      },
      {
        "stnCode": "MDSE",
        "stnName": "MADHU SUDANPUR",
        "arrival": "12:31",
        "departure": "12:31"
      },
      {
        "stnCode": "CDAE",
        "stnName": "CHANDANPUR",
        "arrival": "12:34",
        "departure": "12:34"
      },
      {
        "stnCode": "PBZ",
        "stnName": "PORABAZAR",
        "arrival": "12:38",
        "departure": "12:38"
      },
      {
        "stnCode": "BMAE",
        "stnName": "BELMURI",
        "arrival": "12:39",
        "departure": "12:39"
      },
      {
        "stnCode": "DNHL",
        "stnName": "DHANIAKHALI",
        "arrival": "12:41",
        "departure": "12:41"
      },
      {
        "stnCode": "SHBC",
        "stnName": "SIBAICHANDI",
        "arrival": "12:43",
        "departure": "12:43"
      },
      {
        "stnCode": "HIH",
        "stnName": "HAJIGARH",
        "arrival": "12:46",
        "departure": "12:46"
      },
      {
        "stnCode": "GRAE",
        "stnName": "GURAP",
        "arrival": "12:47",
        "departure": "12:47"
      },
      {
        "stnCode": "JPQ",
        "stnName": "JHAPANDANGA",
        "arrival": "12:51",
        "departure": "12:51"
      },
      {
        "stnCode": "JRAE",
        "stnName": "JAUGRAM",
        "arrival": "12:52",
        "departure": "12:52"
      },
      {
        "stnCode": "NBAE",
        "stnName": "NABAGRAM",
        "arrival": "12:54",
        "departure": "12:54"
      },
      {
        "stnCode": "MSAE",
        "stnName": "MASAGRAM",
        "arrival": "12:58",
        "departure": "12:58"
      },
      {
        "stnCode": "CHC",
        "stnName": "CHANCHAI",
        "arrival": "13:00",
        "departure": "13:00"
      },
      {
        "stnCode": "PRAE",
        "stnName": "PALLA ROAD",
        "arrival": "13:03",
        "departure": "13:03"
      },
      {
        "stnCode": "SKG",
        "stnName": "SAKTIGARH",
        "arrival": "13:06",
        "departure": "13:06"
      },
      {
        "stnCode": "GRP",
        "stnName": "GANGPUR",
        "arrival": "13:10",
        "departure": "13:10"
      },
      {
        "stnCode": "BWN",
        "stnName": "BARDDHAMAN JN",
        "arrival": "13:15",
        "departure": "13:17"
      },
      {
        "stnCode": "TIT",
        "stnName": "TALIT",
        "arrival": "13:26",
        "departure": "13:26"
      },
      {
        "stnCode": "KAN",
        "stnName": "KHANA JN",
        "arrival": "13:32",
        "departure": "13:32"
      },
      {
        "stnCode": "JTL",
        "stnName": "JHAPATER DHAL",
        "arrival": "13:39",
        "departure": "13:39"
      },
      {
        "stnCode": "BPS",
        "stnName": "BANPAS",
        "arrival": "13:44",
        "departure": "13:44"
      },
      {
        "stnCode": "NRX",
        "stnName": "NOADAR DHAL",
        "arrival": "13:48",
        "departure": "13:48"
      },
      {
        "stnCode": "GKH",
        "stnName": "GUSKARA",
        "arrival": "13:54",
        "departure": "13:55"
      },
      {
        "stnCode": "PCQ",
        "stnName": "PICHKURIRDHAL",
        "arrival": "14:02",
        "departure": "14:02"
      },
      {
        "stnCode": "BDH",
        "stnName": "BHEDIA",
        "arrival": "14:07",
        "departure": "14:07"
      },
      {
        "stnCode": "BHP",
        "stnName": "BOLPUR SHANTINIKETAN",
        "arrival": "14:15",
        "departure": "14:17"
      },
      {
        "stnCode": "PNE",
        "stnName": "PRANTIK",
        "arrival": "14:25",
        "departure": "14:26"
      },
      {
        "stnCode": "KPLE",
        "stnName": "KOPAI",
        "arrival": "14:34",
        "departure": "14:34"
      },
      {
        "stnCode": "AMP",
        "stnName": "AHMADPUR JN",
        "arrival": "14:42",
        "departure": "14:43"
      },
      {
        "stnCode": "BSLE",
        "stnName": "BATASPUR",
        "arrival": "14:55",
        "departure": "14:55"
      },
      {
        "stnCode": "SNT",
        "stnName": "SAINTHIA",
        "arrival": "14:57",
        "departure": "14:58"
      },
      {
        "stnCode": "GHLE",
        "stnName": "GADADHARPUR",
        "arrival": "15:01",
        "departure": "15:01"
      },
      {
        "stnCode": "MLV",
        "stnName": "MALLARPUR",
        "arrival": "15:19",
        "departure": "15:19"
      },
      {
        "stnCode": "TPF",
        "stnName": "TARAPITH ROAD",
        "arrival": "15:26",
        "departure": "15:26"
      }
    ],
    "RPH": []
  }
}