{
  "17211": {
    "MTM": [
      {
        "stnCode": "CLU",
        "stnName": "Chilakalapudi",
        "arrival": "15:20",
        "departure": "15:20"
      },
      {
        "stnCode": "PAV",
        "stnName": "Pedana",
        "arrival": "15:27",
        "departure": "15:27"
      },
      {
        "stnCode": "VMD",
        "stnName": "Vadlamannadu",
        "arrival": "15:36",
        "departure": "15:36"
      },
      {
        "stnCode": "GVL",
        "stnName": "Gudlavalleru",
        "arrival": "15:45",
        "departure": "15:45"
      },
      {
        "stnCode": "NUJ",
        "stnName": "Nujella",
        "arrival": "15:51",
        "departure": "15:51"
      },
      {
        "stnCode": "GDV",
        "stnName": "GUDIVADA JN",
        "arrival": "15:58",
        "departure": "16:00"
      },
      {
        "stnCode": "DPD",
        "stnName": "DOSAPADU",
        "arrival": "16:09",
        "departure": "16:09"
      },
      {
        "stnCode": "VPG",
        "stnName": "VENTRAPRAGADA",
        "arrival": "16:13",
        "departure": "16:13"
      },
      {
        "stnCode": "IDP",
        "stnName": "INDUPALLI",
        "arrival": "16:19",
        "departure": "16:19"
      },
      {
        "stnCode": "TGU",
        "stnName": "TARIGOPPULA",
        "arrival": "16:25",
        "departure": "16:25"
      },
      {
        "stnCode": "UPL",
        "stnName": "UPPALUR",
        "arrival": "16:33",
        "departure": "16:33"
      },
      {
        "stnCode": "NDM",
        "stnName": "NIDAMANURU",
        "arrival": "16:41",
        "departure": "16:41"
      },
      {
        "stnCode": "RMV",
        "stnName": "RAMAVARAPPADU",
        "arrival": "16:48",
        "departure": "16:48"
      }
    ],
    "BZA": [
      {
        "stnCode": "KCC",
        "stnName": "KRISHNA CANAL",
        "arrival": "17:18",
        "departure": "17:18"
      },
      {
        "stnCode": "MAG",
        "stnName": "MANGALAGIRI",
        "arrival": "17:28",
        "departure": "17:28"
      },
      {
        "stnCode": "NBR",
        "stnName": "NAMBURU",
        "arrival": "17:47",
        "departure": "17:47"
      }
    ],
    "GNT": [
      {
        "stnCode": "NLPD",
        "stnName": "NALLAPADU",
        "arrival": "18:10",
        "departure": "18:10"
      },
      {
        "stnCode": "PRCA",
        "stnName": "PERECHERLA",
        "arrival": "18:16",
        "departure": "18:16"
      },
      {
        "stnCode": "PPM",
        "stnName": "PHIRANGIPURAM",
        "arrival": "18:25",
        "departure": "18:25"
      },
      {
        "stnCode": "NDPU",
        "stnName": "NUDURUPADU",
        "arrival": "18:32",
        "departure": "18:32"
      },
      {
        "stnCode": "STUR",
        "stnName": "SATULUR",
        "arrival": "18:38",
        "departure": "18:38"
      },
      {
        "stnCode": "NRT",
        "stnName": "NARASARAOPET",
        "arrival": "18:49",
        "departure": "18:49"
      },
      {
        "stnCode": "MUK",
        "stnName": "MUNUMAKA",
        "arrival": "18:56",
        "departure": "18:56"
      },
      {
        "stnCode": "SAB",
        "stnName": "SANTAMAGULUR",
        "arrival": "19:04",
        "departure": "19:04"
      },
      {
        "stnCode": "VEP",
        "stnName": "Velpuru Road",
        "arrival": "19:08",
        "departure": "19:08"
      },
      {
        "stnCode": "SYM",
        "stnName": "SAVALYAPURAM",
        "arrival": "19:16",
        "departure": "19:16"
      },
      {
        "stnCode": "VKN",
        "stnName": "VINUKONDA",
        "arrival": "19:25",
        "departure": "19:25"
      },
      {
        "stnCode": "CEM",
        "stnName": "CHEEKATEEGALPLM",
        "arrival": "19:33",
        "departure": "19:33"
      },
      {
        "stnCode": "GKM",
        "stnName": "GUNDALUKAMMA",
        "arrival": "19:38",
        "departure": "19:38"
      },
      {
        "stnCode": "KCD",
        "stnName": "KURICHEDU",
        "arrival": "19:49",
        "departure": "19:49"
      },
      {
        "stnCode": "POO",
        "stnName": "POTLAPADU",
        "arrival": "19:55",
        "departure": "19:55"
      },
      {
        "stnCode": "DKD",
        "stnName": "DONAKONDA",
        "arrival": "20:00",
        "departure": "20:01"
      },
      {
        "stnCode": "GJJ",
        "stnName": "GAJJELAKONDA",
        "arrival": "20:12",
        "departure": "20:12"
      },
      {
        "stnCode": "MRK",
        "stnName": "MARKAPUR ROAD",
        "arrival": "20:24",
        "departure": "20:25"
      },
      {
        "stnCode": "TLU",
        "stnName": "TARLUPADU",
        "arrival": "20:33",
        "departure": "20:33"
      },
      {
        "stnCode": "CBM",
        "stnName": "CUMBUM",
        "arrival": "20:44",
        "departure": "20:45"
      },
      {
        "stnCode": "JBK",
        "stnName": "JAGGAMBOTLA KRISHNAPURAM",
        "arrival": "20:52",
        "departure": "20:52"
      },
      {
        "stnCode": "SDV",
        "stnName": "SOMIDEVIPALLE",
        "arrival": "21:05",
        "departure": "21:05"
      },
      {
        "stnCode": "GMA",
        "stnName": "GUDIMETTA",
        "arrival": "21:10",
        "departure": "21:10"
      },
      {
        "stnCode": "GID",
        "stnName": "GIDDALUR",
        "arrival": "21:20",
        "departure": "21:21"
      },
      {
        "stnCode": "KSTE",
        "stnName": "KISTAMSETTIPALI",
        "arrival": "21:29",
        "departure": "21:29"
      },
      {
        "stnCode": "DMT",
        "stnName": "DIGUVAMETTA",
        "arrival": "21:39",
        "departure": "21:39"
      },
      {
        "stnCode": "CMZ",
        "stnName": "CHALAMA",
        "arrival": "22:05",
        "departure": "22:05"
      },
      {
        "stnCode": "GZL",
        "stnName": "GAZULAPALLI",
        "arrival": "22:22",
        "departure": "22:22"
      }
    ],
    "NDL": [
      {
        "stnCode": "PNM",
        "stnName": "PANYAM",
        "arrival": "23:04",
        "departure": "23:04"
      },
      {
        "stnCode": "KEF",
        "stnName": "KRISHNAMA KONA",
        "arrival": "23:13",
        "departure": "23:13"
      },
      {
        "stnCode": "BEY",
        "stnName": "B CEMENT NAGAR",
        "arrival": "23:22",
        "departure": "23:22"
      },
      {
        "stnCode": "BMH",
        "stnName": "BETAMCHERLA",
        "arrival": "23:28",
        "departure": "23:28"
      },
      {
        "stnCode": "RGM",
        "stnName": "RANGAPURAM",
        "arrival": "23:38",
        "departure": "23:38"
      },
      {
        "stnCode": "MLK",
        "stnName": "MALKAPURAM",
        "arrival": "23:49",
        "departure": "23:49"
      },
      {
        "stnCode": "DHNE",
        "stnName": "DHONE",
        "arrival": "00:01",
        "departure": "00:05"
      },
      {
        "stnCode": "MYL",
        "stnName": "MALLIYALA",
        "arrival": "00:32",
        "departure": "00:32"
      },
      {
        "stnCode": "LMD",
        "stnName": "LINGANENIDODDI",
        "arrival": "00:56",
        "departure": "00:56"
      },
      {
        "stnCode": "PDL",
        "stnName": "PENDEKALLU",
        "arrival": "01:13",
        "departure": "01:13"
      },
      {
        "stnCode": "GY",
        "stnName": "GOOTY JN",
        "arrival": "02:29",
        "departure": "02:30"
      },
      {
        "stnCode": "RRJ",
        "stnName": "RAMARAJU PALLI",
        "arrival": "02:53",
        "departure": "02:53"
      },
      {
        "stnCode": "KLU",
        "stnName": "KALLURU",
        "arrival": "03:17",
        "departure": "03:17"
      },
      {
        "stnCode": "GDE",
        "stnName": "GARLADINNE",
        "arrival": "03:34",
        "departure": "03:34"
      },
      {
        "stnCode": "ATP",
        "stnName": "ANANTAPUR",
        "arrival": "03:59",
        "departure": "04:00"
      },
      {
        "stnCode": "ZPL",
        "stnName": "ZANGALAPALLE",
        "arrival": "04:27",
        "departure": "04:27"
      },
      {
        "stnCode": "CCA",
        "stnName": "CHIGICHERLA",
        "arrival": "04:47",
        "departure": "04:47"
      }
    ],
    "DMM": [
      {
        "stnCode": "BSPL",
        "stnName": "BASAMPALLE",
        "arrival": "05:29",
        "departure": "05:29"
      },
      {
        "stnCode": "KTCR",
        "stnName": "KOTHACHERUVU",
        "arrival": "05:43",
        "departure": "05:43"
      },
      {
        "stnCode": "SSPN",
        "stnName": "SATYA SAI P NILAYAM",
        "arrival": "05:45",
        "departure": "05:47"
      },
      {
        "stnCode": "NRYP",
        "stnName": "NARAYANAPURAM",
        "arrival": "05:57",
        "departure": "05:57"
      },
      {
        "stnCode": "PKD",
        "stnName": "PENUKONDA",
        "arrival": "06:11",
        "departure": "06:11"
      },
      {
        "stnCode": "CPL",
        "stnName": "CHAKARLAPALLI",
        "arrival": "06:29",
        "departure": "06:29"
      },
      {
        "stnCode": "MLU",
        "stnName": "MALUGUR",
        "arrival": "06:47",
        "departure": "06:47"
      },
      {
        "stnCode": "HUP",
        "stnName": "HINDUPUR",
        "arrival": "06:57",
        "departure": "06:58"
      },
      {
        "stnCode": "VWA",
        "stnName": "VIDURASWATTHA",
        "arrival": "07:26",
        "departure": "07:26"
      },
      {
        "stnCode": "GBD",
        "stnName": "GAURIBIDANUR",
        "arrival": "07:36",
        "departure": "07:36"
      },
      {
        "stnCode": "SMWA",
        "stnName": "SOMESHWARA",
        "arrival": "07:46",
        "departure": "07:46"
      },
      {
        "stnCode": "TDV",
        "stnName": "THONDEBHAVI",
        "arrival": "07:58",
        "departure": "07:58"
      },
      {
        "stnCode": "MKL",
        "stnName": "MAKLIDRUG",
        "arrival": "08:12",
        "departure": "08:12"
      },
      {
        "stnCode": "ORH",
        "stnName": "ODDARAHALLI",
        "arrival": "08:29",
        "departure": "08:29"
      },
      {
        "stnCode": "DBU",
        "stnName": "DODBALLAPUR",
        "arrival": "08:41",
        "departure": "08:41"
      },
      {
        "stnCode": "RNN",
        "stnName": "RAJANKUNTI",
        "arrival": "09:01",
        "departure": "09:01"
      },
      {
        "stnCode": "YNK",
        "stnName": "YELHANKA JN",
        "arrival": "09:13",
        "departure": "09:15"
      },
      {
        "stnCode": "KDGH",
        "stnName": "KODIGEHALLI",
        "arrival": "09:27",
        "departure": "09:27"
      },
      {
        "stnCode": "LOGH",
        "stnName": "LOTTEGOLLAHALLI",
        "arrival": "09:33",
        "departure": "09:33"
      }
    ],
    "YPR": []
  }
}