{
  "52408": {
    "SGNR": [
      {
        "stnCode": "BWC",
        "stnName": "Banwali",
        "arrival": "16:16",
        "departure": "16:17"
      },
      {
        "stnCode": "FSW",
        "stnName": "Fateh Singhwala",
        "arrival": "16:26",
        "departure": "16:27"
      },
      {
        "stnCode": "SDS",
        "stnName": "Sadulshahr",
        "arrival": "16:36",
        "departure": "16:37"
      },
      {
        "stnCode": "BDSW",
        "stnName": "Budhsinghwala",
        "arrival": "16:53",
        "departure": "16:54"
      },
      {
        "stnCode": "BUGL",
        "stnName": "Buglanwali",
        "arrival": "17:03",
        "departure": "17:04"
      },
      {
        "stnCode": "DPK",
        "stnName": "Dholipal",
        "arrival": "17:12",
        "departure": "17:13"
      },
      {
        "stnCode": "HLW",
        "stnName": "Hirnawali",
        "arrival": "17:21",
        "departure": "17:22"
      },
      {
        "stnCode": "JRKN",
        "stnName": "Jorkian",
        "arrival": "17:29",
        "departure": "17:30"
      }
    ],
    "HMH": [
      {
        "stnCode": "HMO",
        "stnName": "Hanumangarh Town",
        "arrival": "18:07",
        "departure": "18:08"
      },
      {
        "stnCode": "SRKN",
        "stnName": "Sherekan",
        "arrival": "18:21",
        "departure": "18:22"
      },
      {
        "stnCode": "SJSM",
        "stnName": "Salemgarhmasani",
        "arrival": "18:27",
        "departure": "18:28"
      },
      {
        "stnCode": "TIBI",
        "stnName": "Tibi",
        "arrival": "18:34",
        "departure": "18:35"
      },
      {
        "stnCode": "TLI",
        "stnName": "Tulwara Jhil",
        "arrival": "18:46",
        "departure": "18:47"
      },
      {
        "stnCode": "ENB",
        "stnName": "Ellenabad",
        "arrival": "18:59",
        "departure": "19:00"
      },
      {
        "stnCode": "SURR",
        "stnName": "Surera",
        "arrival": "19:09",
        "departure": "19:10"
      },
      {
        "stnCode": "KNNA",
        "stnName": "Khinaniyan",
        "arrival": "19:19",
        "departure": "19:20"
      },
      {
        "stnCode": "BKKA",
        "stnName": "Bhukarka",
        "arrival": "19:34",
        "departure": "19:35"
      },
      {
        "stnCode": "NHR",
        "stnName": "Nohar",
        "arrival": "19:43",
        "departure": "19:44"
      },
      {
        "stnCode": "DPLN",
        "stnName": "Diplana",
        "arrival": "19:57",
        "departure": "19:58"
      },
      {
        "stnCode": "SHRG",
        "stnName": "Sri Ramgarh Halt",
        "arrival": "20:09",
        "departure": "20:10"
      },
      {
        "stnCode": "GAMI",
        "stnName": "Gogameri",
        "arrival": "20:22",
        "departure": "20:23"
      },
      {
        "stnCode": "TSD",
        "stnName": "Tahsil Bhadra",
        "arrival": "20:40",
        "departure": "20:41"
      },
      {
        "stnCode": "KALN",
        "stnName": "Kalana",
        "arrival": "20:56",
        "departure": "20:57"
      },
      {
        "stnCode": "AUS",
        "stnName": "Anupshahr",
        "arrival": "21:07",
        "departure": "21:08"
      },
      {
        "stnCode": "SDMK",
        "stnName": "Sidmukh",
        "arrival": "21:22",
        "departure": "21:23"
      },
      {
        "stnCode": "HSWS",
        "stnName": "Hansiawas",
        "arrival": "21:34",
        "departure": "21:35"
      },
      {
        "stnCode": "NRWI",
        "stnName": "Narwasi",
        "arrival": "21:47",
        "departure": "21:48"
      },
      {
        "stnCode": "SURP",
        "stnName": "Suratpura",
        "arrival": "22:25",
        "departure": "22:25"
      }
    ],
    "SDLP": []
  }
}