{
  "54341": {
    "SRE": [
      {
        "stnCode": "BAE",
        "stnName": "BALIAKHERI",
        "arrival": "14:45",
        "departure": "14:46"
      },
      {
        "stnCode": "SNKE",
        "stnName": "SUNEHTI KHARKHARI",
        "arrival": "14:54",
        "departure": "14:55"
      },
      {
        "stnCode": "CDL",
        "stnName": "CHODIALA",
        "arrival": "15:03",
        "departure": "15:04"
      },
      {
        "stnCode": "IQB",
        "stnName": "IQBALPUR",
        "arrival": "15:13",
        "departure": "15:14"
      },
      {
        "stnCode": "RK",
        "stnName": "ROORKEE",
        "arrival": "15:23",
        "departure": "15:24"
      },
      {
        "stnCode": "DNRA",
        "stnName": "DHANDHERA",
        "arrival": "15:33",
        "departure": "15:34"
      },
      {
        "stnCode": "LDR",
        "stnName": "LANDAURA",
        "arrival": "15:41",
        "departure": "15:42"
      },
      {
        "stnCode": "DSNI",
        "stnName": "DAUSNI",
        "arrival": "15:49",
        "departure": "15:50"
      }
    ],
    "LRJ": [
      {
        "stnCode": "ATMO",
        "stnName": "AITHAL",
        "arrival": "16:54",
        "departure": "16:55"
      },
      {
        "stnCode": "PRI",
        "stnName": "PATHRI",
        "arrival": "17:03",
        "departure": "17:04"
      },
      {
        "stnCode": "IKK",
        "stnName": "IKKAR",
        "arrival": "17:12",
        "departure": "17:13"
      },
      {
        "stnCode": "JWP",
        "stnName": "JWALAPUR",
        "arrival": "17:22",
        "departure": "17:23"
      }
    ],
    "HW": [
      {
        "stnCode": "MOTC",
        "stnName": "MOTICHUR",
        "arrival": "17:54",
        "departure": "17:55"
      },
      {
        "stnCode": "RWL",
        "stnName": "RAIWALA",
        "arrival": "18:14",
        "departure": "18:15"
      },
      {
        "stnCode": "QSR",
        "stnName": "KANSRAO",
        "arrival": "18:32",
        "departure": "18:33"
      },
      {
        "stnCode": "DWO",
        "stnName": "DOIWALA",
        "arrival": "18:49",
        "departure": "18:50"
      },
      {
        "stnCode": "HRW",
        "stnName": "HARRAWALA",
        "arrival": "19:13",
        "departure": "19:14"
      }
    ],
    "DDN": []
  }
}