{
  "58835": {
    "NGP": [],
    "ITR": [
      {
        "stnCode": "KRDH",
        "stnName": "Koradih",
        "arrival": "16:25",
        "departure": "16:25"
      },
      {
        "stnCode": "KPKD",
        "stnName": "Khapri Kheda",
        "arrival": "16:40",
        "departure": "16:42"
      },
      {
        "stnCode": "PQA",
        "stnName": "Pipla Halt",
        "arrival": "16:58",
        "departure": "16:58"
      },
      {
        "stnCode": "PSX",
        "stnName": "Patansaongi Town Halt",
        "arrival": "17:04",
        "departure": "17:06"
      },
      {
        "stnCode": "PTS",
        "stnName": "Patansaongi",
        "arrival": "17:10",
        "departure": "17:10"
      },
      {
        "stnCode": "TKLB",
        "stnName": "Takli Bhansali",
        "arrival": "17:15",
        "departure": "17:15"
      },
      {
        "stnCode": "MGVK",
        "stnName": "Malegaon Vyenku",
        "arrival": "17:22",
        "departure": "17:22"
      }
    ],
    "SONR": [
      {
        "stnCode": "KLOD",
        "stnName": "Kelod",
        "arrival": "17:57",
        "departure": "17:59"
      },
      {
        "stnCode": "SZH",
        "stnName": "Saonga Halt",
        "arrival": "18:12",
        "departure": "18:14"
      },
      {
        "stnCode": "PSK",
        "stnName": "Paradsinga Halt",
        "arrival": "18:20",
        "departure": "18:22"
      },
      {
        "stnCode": "LDE",
        "stnName": "Lokdhikhera",
        "arrival": "18:31",
        "departure": "18:33"
      },
      {
        "stnCode": "BDHT",
        "stnName": "Bardi Halt",
        "arrival": "18:45",
        "departure": "18:45"
      },
      {
        "stnCode": "SASR",
        "stnName": "Sausar",
        "arrival": "18:58",
        "departure": "19:00"
      },
      {
        "stnCode": "RMO",
        "stnName": "Ramakona",
        "arrival": "19:14",
        "departure": "19:16"
      },
      {
        "stnCode": "DVH",
        "stnName": "Devi Halt",
        "arrival": "19:26",
        "departure": "19:28"
      },
      {
        "stnCode": "GELA",
        "stnName": "Ghadela Halt",
        "arrival": "19:33",
        "departure": "19:33"
      },
      {
        "stnCode": "BMC",
        "stnName": "Bhimalgondi",
        "arrival": "19:46",
        "departure": "19:48"
      },
      {
        "stnCode": "MPML",
        "stnName": "Mohapani Mal",
        "arrival": "20:04",
        "departure": "20:04"
      },
      {
        "stnCode": "KFP",
        "stnName": "Kukra Khapa",
        "arrival": "20:33",
        "departure": "20:35"
      },
      {
        "stnCode": "ULA",
        "stnName": "Umra Nala",
        "arrival": "21:02",
        "departure": "21:04"
      },
      {
        "stnCode": "BRKH",
        "stnName": "Bisapur Kalan Halt",
        "arrival": "21:15",
        "departure": "21:15"
      },
      {
        "stnCode": "LIG",
        "stnName": "Linga",
        "arrival": "21:26",
        "departure": "21:28"
      }
    ],
    "CWA": []
  }
}