{
  "58868": {
    "JBP": [],
    "HBG": [
      {
        "stnCode": "GRG",
        "stnName": "Guwarighat",
        "arrival": "18:43",
        "departure": "18:45"
      },
      {
        "stnCode": "JPV",
        "stnName": "Jamtara Paraswara",
        "arrival": "18:59",
        "departure": "19:01"
      },
      {
        "stnCode": "CRE",
        "stnName": "Charghat Piparia",
        "arrival": "19:16",
        "departure": "19:18"
      },
      {
        "stnCode": "BUQ",
        "stnName": "Bargi",
        "arrival": "19:31",
        "departure": "19:33"
      },
      {
        "stnCode": "SOY",
        "stnName": "Sukrimangela",
        "arrival": "19:50",
        "departure": "19:52"
      },
      {
        "stnCode": "BUQ",
        "stnName": "Bargi",
        "arrival": "19:58",
        "departure": "19:58"
      },
      {
        "stnCode": "KDHI",
        "stnName": "Kaladehi",
        "arrival": "19:58",
        "departure": "20:00"
      },
      {
        "stnCode": "DRPH",
        "stnName": "Devri P.H.",
        "arrival": "20:07",
        "departure": "20:09"
      },
      {
        "stnCode": "SKY",
        "stnName": "Shikara",
        "arrival": "20:24",
        "departure": "20:26"
      },
      {
        "stnCode": "VNK",
        "stnName": "Binaiki",
        "arrival": "20:56",
        "departure": "20:58"
      },
      {
        "stnCode": "GNS",
        "stnName": "Ghonsor",
        "arrival": "21:24",
        "departure": "21:26"
      },
      {
        "stnCode": "NDNI",
        "stnName": "Nidhani",
        "arrival": "21:53",
        "departure": "21:55"
      },
      {
        "stnCode": "TPNI",
        "stnName": "Tuiya Pani",
        "arrival": "22:20",
        "departure": "22:22"
      },
      {
        "stnCode": "PDE",
        "stnName": "Pindrai",
        "arrival": "22:25",
        "departure": "22:27"
      },
      {
        "stnCode": "JONR",
        "stnName": "Jeonara Ph",
        "arrival": "22:41",
        "departure": "22:43"
      }
    ],
    "NIR": [
      {
        "stnCode": "PNJ",
        "stnName": "Padriganj",
        "arrival": "00:36",
        "departure": "00:38"
      },
      {
        "stnCode": "NWA",
        "stnName": "Nagarwara",
        "arrival": "01:00",
        "departure": "01:02"
      },
      {
        "stnCode": "LTA",
        "stnName": "Lamta",
        "arrival": "01:18",
        "departure": "01:20"
      },
      {
        "stnCode": "CRN",
        "stnName": "Charegaon",
        "arrival": "01:41",
        "departure": "01:43"
      },
      {
        "stnCode": "TTW",
        "stnName": "Titwa",
        "arrival": "01:48",
        "departure": "01:48"
      },
      {
        "stnCode": "SMC",
        "stnName": "Samnapur",
        "arrival": "02:07",
        "departure": "02:09"
      },
      {
        "stnCode": "DPW",
        "stnName": "Dhapewara",
        "arrival": "02:32",
        "departure": "02:32"
      }
    ],
    "BTC": []
  }
}