{
  "59718": {
    "RE": [
      {
        "stnCode": "KORI",
        "stnName": "Khori",
        "arrival": "19:15",
        "departure": "19:17"
      },
      {
        "stnCode": "KUND",
        "stnName": "Kund",
        "arrival": "19:29",
        "departure": "19:30"
      },
      {
        "stnCode": "KTWS",
        "stnName": "Kathuwas",
        "arrival": "19:36",
        "departure": "19:37"
      },
      {
        "stnCode": "AEL",
        "stnName": "Ateli",
        "arrival": "19:48",
        "departure": "19:49"
      },
      {
        "stnCode": "MBV",
        "stnName": "Mirzapur Bachhaud",
        "arrival": "19:56",
        "departure": "19:57"
      },
      {
        "stnCode": "NNL",
        "stnName": "Narnaul",
        "arrival": "20:04",
        "departure": "20:06"
      },
      {
        "stnCode": "APJ",
        "stnName": "Amarpur Jorasi",
        "arrival": "20:16",
        "departure": "20:17"
      },
      {
        "stnCode": "NIP",
        "stnName": "Nizampur",
        "arrival": "20:23",
        "departure": "20:25"
      },
      {
        "stnCode": "DBLA",
        "stnName": "Dabla",
        "arrival": "20:34",
        "departure": "20:36"
      },
      {
        "stnCode": "JLLO",
        "stnName": "Jhilo",
        "arrival": "20:46",
        "departure": "20:47"
      },
      {
        "stnCode": "MADA",
        "stnName": "Maonda",
        "arrival": "20:56",
        "departure": "20:57"
      },
      {
        "stnCode": "NMK",
        "stnName": "Nim Ka Thana",
        "arrival": "21:06",
        "departure": "21:08"
      },
      {
        "stnCode": "BAGA",
        "stnName": "Bhagega",
        "arrival": "21:18",
        "departure": "21:19"
      },
      {
        "stnCode": "KAWT",
        "stnName": "Kanwat",
        "arrival": "21:30",
        "departure": "21:31"
      },
      {
        "stnCode": "KHRA",
        "stnName": "Khachera",
        "arrival": "21:40",
        "departure": "21:41"
      },
      {
        "stnCode": "SMPR",
        "stnName": "Shri Madhopur",
        "arrival": "21:50",
        "departure": "21:51"
      }
    ],
    "RGS": [
      {
        "stnCode": "KMNP",
        "stnName": "Kishan Manpura",
        "arrival": "22:20",
        "departure": "22:22"
      },
      {
        "stnCode": "BDHL",
        "stnName": "Badhal",
        "arrival": "22:30",
        "departure": "22:31"
      },
      {
        "stnCode": "PCMK",
        "stnName": "Pacharmalikpura",
        "arrival": "22:39",
        "departure": "22:40"
      },
      {
        "stnCode": "RNW",
        "stnName": "Renwal",
        "arrival": "22:46",
        "departure": "22:48"
      },
      {
        "stnCode": "MNHA",
        "stnName": "Mindha",
        "arrival": "22:55",
        "departure": "22:56"
      },
      {
        "stnCode": "BILA",
        "stnName": "Bheslana",
        "arrival": "23:02",
        "departure": "23:03"
      },
      {
        "stnCode": "SFE",
        "stnName": "Sanodiya",
        "arrival": "23:11",
        "departure": "23:12"
      },
      {
        "stnCode": "KNDL",
        "stnName": "Khandel",
        "arrival": "23:18",
        "departure": "23:20"
      },
      {
        "stnCode": "PKBS",
        "stnName": "Peeplee-ka-bas",
        "arrival": "23:27",
        "departure": "23:28"
      }
    ],
    "FL": []
  }
}